ddevdb/__init__.py
ddevdb/cli.py
ddevdb/db.py
ddevdb/backends/__init__.py
ddevdb/backends/base.py
ddevdb/backends/csv_backend.py
ddevdb/backends/inmemory_backend.py
ddevdb/backends/json_backend.py
ddevdb/backends/pickle_backend.py
ddevdb-0.0.9.dist-info/METADATA
ddevdb-0.0.9.dist-info/WHEEL
ddevdb-0.0.9.dist-info/top_level.txt
ddevdb-0.0.9.dist-info/RECORD
