Metadata-Version: 2.4
Name: ddevdb
Version: 0.0.9
Summary: A Lightweight database. Supports multiple backends
Author: ddavidel
Project-URL: Homepage, https://github.com/ddavidel/ddevdb
Requires-Python: >=3.7
Requires-Dist: platformdirs==4.3.8
